opyrator/__init__.py
opyrator/_about.py
opyrator/_cli.py
opyrator/core.py
opyrator/export.py
opyrator/api/__init__.py
opyrator/api/fastapi_app.py
opyrator/api/fastapi_utils.py
opyrator/components/__init__.py
opyrator/components/outputs.py
opyrator/components/types.py
opyrator/tasks/__init__.py
opyrator/ui/__init__.py
opyrator/ui/schema_utils.py
opyrator/ui/streamlit_ui.py
opyrator/ui/streamlit_utils.py
opyrator/utils/__init__.py
opyrator-0.0.12.dist-info/LICENSE
opyrator-0.0.12.dist-info/METADATA
opyrator-0.0.12.dist-info/WHEEL
opyrator-0.0.12.dist-info/entry_points.txt
opyrator-0.0.12.dist-info/top_level.txt
opyrator-0.0.12.dist-info/RECORD
